ks_ci/__init__.py
ks_ci/discord.py
ks_ci/junit.py
ks_ci-1.3.1.data/scripts/ks_ci_helper.py
ks_ci-1.3.1.dist-info/LICENSE
ks_ci-1.3.1.dist-info/METADATA
ks_ci-1.3.1.dist-info/WHEEL
ks_ci-1.3.1.dist-info/top_level.txt
ks_ci-1.3.1.dist-info/RECORD
