Metadata-Version: 2.1
Name: ks-ci
Version: 1.3.1
Summary: KS CI Bundle
Home-page: https://github.com/poleszcz/ks-ci-bundle
Author: Maciej Poleszczyk
Author-email: mpoleszczyk@wp.pl
License: MIT
Platform: UNKNOWN
Requires-Python: >=3
